{
  "type": "silentgear:standard",
  "simple": true,
  "availability": {
    "tier": 6,
    "categories": [
      "metal"
    ],
    "visible": true,
    "gear_blacklist": [],
    "can_salvage": true
  },
  "crafting_items": {
    "main": {
      "tag": "forge:ingots/palladium"
    }
  },
  "name": {
    "text": "Palladium"
  },
  "stats": {
    "main": {
      "durability": 2816.0,
      "armor_durability": 61.0,
      "enchantment_value": 32.0,
      "rarity": 100.0,
      "charging_value": 1.4,
      "harvest_level": 5.0,
      "harvest_speed": 13.0,
      "melee_damage": 7.0,
      "magic_damage": 5.0,
      "attack_speed": 0.2,
      "ranged_damage": 4.0,
      "ranged_speed": 1.5,
      "projectile_speed": 2.5,
      "projectile_accuracy": 3.5,
      "armor": 25.0,
      "armor/helmet": 5.0,
      "armor/chestplate": 9.0,
      "armor/leggings": 7.0,
      "armor/boots": 4.0,
      "armor_toughness": 14.0,
      "magic_armor": 16.0
    },
    "tip": {
      "harvest_speed": {
        "add": 5.0
      },
      "melee_damage": {
        "add": 2.0
      },
      "attack_speed": {
        "add": 0.5
      },
      "harvest_level": {
        "max": 5.0
      }
    }
  },
  "traits": {
    "main": [
      {
        "name": "silentgear:malleable",
        "level": 3,
        "conditions": [
          {
            "type": "silentgear:material_ratio",
            "ratio": 0.5
          }
        ]
      },
      {
        "name": "silentgear:sharp",
        "level": 4,
        "conditions": [
          {
            "type": "silentgear:material_ratio",
            "ratio": 0.5
          }
        ]
      }
    ],
    "tip": [
      {
        "name": "silentgear:malleable",
        "level": 3
      },
      {
        "name": "silentgear:sharp",
        "level": 4
      }
    ]
  },
  "model": {
    "main/all": [
      {
        "texture": "silentgear:main_generic_hc",
        "color": "#FFC70C"
      },
      {
        "texture": "silentgear:_highlight"
      }
    ],
    "main/fragment": [
      {
        "texture": "silentgear:metal",
        "color": "#FFC70C"
      }
    ],
    "tip/all": [
      {
        "texture": "silentgear:tip_sharp",
        "color": "#FFC70C"
      }
    ],
    "tip/part": [
      {
        "texture": "silentgear:tip_base"
      },
      {
        "texture": "silentgear:tip",
        "color": "#FFC70C"
      },
      {
        "texture": "silentgear:tip_shine"
      }
    ]
  }
}