{
  "pools": [
    {
      "name": "main",
      "rolls": 10,
      "entries": [
        {
          "type": "minecraft:item",
          "weight": 9,
          "functions": [
            {
              "function": "minecraft:set_count",
              "count": {
                "min": 1.0,
                "max": 3.0,
                "type": "minecraft:uniform"
              }
            }
          ],
          "name": "minecraft:diamond"
        },
        {
          "type": "minecraft:item",
          "weight": 10,
          "functions": [
            {
              "function": "minecraft:set_count",
              "count": {
                "min": 2.0,
                "max": 4.0,
                "type": "minecraft:uniform"
              }
            }
          ],
          "name": "minecraft:emerald"
        },
        {
          "type": "minecraft:item",
          "weight": 7,
          "functions": [
            {
              "function": "minecraft:set_count",
              "count": {
                "min": 1.0,
                "max": 3.0,
                "type": "minecraft:uniform"
              }
            }
          ],
          "name": "minecraft:prismarine_shard"
        },
        {
          "type": "minecraft:loot_table",
          "name": "meatsalad:gear/random",
          "weight": 22
        },
        {
          "type": "empty",
          "weight": 12
        }
      ]
    },
    {
      "rolls": 1.0,
      "bonus_rolls": 0.0,
      "entries": [
        {
          "type": "minecraft:empty",
          "weight": 70
        },
        {
          "type": "minecraft:loot_table",
          "name": "meatsalad:gems/random",
		      "weight": 30,
          "quality": 1
        }
      ]
    },
    {
      "rolls": 1.0,
      "bonus_rolls": 0.0,
      "entries": [
        {
          "type": "minecraft:empty",
          "weight": 70
        },
        {
          "type": "minecraft:loot_table",
          "name": "meatsalad:affix_item/random",
          "weight": 30,
          "quality": 1
        }
      ]
    },
    {
      "rolls": 1.0,
      "bonus_rolls": 0.0,
      "entries": [
        {
          "type": "minecraft:empty",
          "weight": 80
        },
        {
          "type": "minecraft:loot_table",
          "name": "meatsalad:overworld/misc",
		      "weight": 20,
          "quality": 0.5
        }
      ]
    }
  ]
}