{
  "type": "silentgear:attribute",
  "max_level": 10,
  "additive": true,
  "name": {
    "text": "Mana Regen"
  },
  "description": {
    "text": "Grants additional mana regen"
  },
  "attribute_modifiers": {
    "all": [
      {
        "attribute": "irons_spellbooks:mana_regen",
        "operation": 1,
        "value": [
          0.0125,
          0.025,
          0.0375,
          0.05,
          0.0625,
          0.075,
          0.0875,
          0.1,
          0.1125,
          0.125
        ]
      }
    ]
  }
}